{
  "legislative_session": "2025",
  "identifier": "AB768",
  "title": "Relating to: operation of drones over certain utility facilities and providing a penalty.",
  "from_organization": "~{\"classification\": \"lower\"}",
  "classification": [
    "bill"
  ],
  "subject": [],
  "abstracts": [],
  "other_titles": [],
  "other_identifiers": [
    {
      "identifier": "ocd-bill-wi-2025-ab768"
    }
  ],
  "actions": [
    {
      "description": "Introduced by Representatives Donovan, Dittrich, Goodwin, Knodl, Maxey, Melotik, Murphy, Novak, O'Connor, Penterman, Sinicki, Tittl and Wichgers; \ncosponsored by Senators Tomczyk and James",
      "date": "2025-12-17T06:00:00+00:00",
      "organization_id": "~{\"classification\": \"lower\"}",
      "classification": [
        "introduction"
      ],
      "related_entities": [],
      "_processing": {
        "log_file_created": "2026-07-15T13:15:17Z"
      }
    },
    {
      "description": "Read first time and referred to Committee on Criminal Justice and Public Safety",
      "date": "2025-12-17T06:00:00+00:00",
      "organization_id": "~{\"classification\": \"lower\"}",
      "classification": [
        "reading-1",
        "referral-committee"
      ],
      "related_entities": [],
      "_processing": {
        "log_file_created": "2026-07-15T13:15:17Z"
      }
    },
    {
      "description": "LRB correction",
      "date": "2026-01-06T06:00:00+00:00",
      "organization_id": "~{\"classification\": \"lower\"}",
      "classification": [],
      "related_entities": [],
      "_processing": {
        "log_file_created": "2026-07-15T13:15:17Z"
      }
    },
    {
      "description": "Public hearing held",
      "date": "2026-01-14T06:00:00+00:00",
      "organization_id": "~{\"classification\": \"lower\"}",
      "classification": [],
      "related_entities": [],
      "_processing": {
        "log_file_created": "2026-07-15T13:15:17Z"
      }
    },
    {
      "description": "Assembly Amendment 1 offered by Representative Donovan",
      "date": "2026-01-16T06:00:00+00:00",
      "organization_id": "~{\"classification\": \"lower\"}",
      "classification": [
        "amendment-introduction"
      ],
      "related_entities": [],
      "_processing": {
        "log_file_created": "2026-07-15T13:15:17Z"
      }
    },
    {
      "description": "Executive action taken",
      "date": "2026-01-21T06:00:00+00:00",
      "organization_id": "~{\"classification\": \"lower\"}",
      "classification": [],
      "related_entities": [],
      "_processing": {
        "log_file_created": "2026-07-15T13:15:17Z"
      }
    },
    {
      "description": "Report Assembly Amendment 1 adoption recommended by Committee on Criminal Justice and Public Safety, Ayes 15, Noes 0",
      "date": "2026-01-22T06:00:00+00:00",
      "organization_id": "~{\"classification\": \"lower\"}",
      "classification": [
        "committee-passage-favorable"
      ],
      "related_entities": [],
      "_processing": {
        "log_file_created": "2026-07-15T13:15:17Z"
      }
    },
    {
      "description": "Report passage as amended recommended by Committee on Criminal Justice and Public Safety, Ayes 13, Noes 2",
      "date": "2026-01-22T06:00:00+00:00",
      "organization_id": "~{\"classification\": \"lower\"}",
      "classification": [
        "committee-passage-favorable"
      ],
      "related_entities": [],
      "_processing": {
        "log_file_created": "2026-07-15T13:15:17Z"
      }
    },
    {
      "description": "Referred to committee on Rules",
      "date": "2026-01-22T06:00:00+00:00",
      "organization_id": "~{\"classification\": \"lower\"}",
      "classification": [
        "referral-committee"
      ],
      "related_entities": [],
      "_processing": {
        "log_file_created": "2026-07-15T13:15:17Z"
      }
    },
    {
      "description": "Assembly Amendment 2 offered by Representative Donovan",
      "date": "2026-01-30T06:00:00+00:00",
      "organization_id": "~{\"classification\": \"lower\"}",
      "classification": [
        "amendment-introduction"
      ],
      "related_entities": [],
      "_processing": {
        "log_file_created": "2026-07-15T13:15:17Z"
      }
    },
    {
      "description": "Representative McCarville added as a coauthor",
      "date": "2026-02-11T06:00:00+00:00",
      "organization_id": "~{\"classification\": \"lower\"}",
      "classification": [],
      "related_entities": [],
      "_processing": {
        "log_file_created": "2026-07-15T13:15:17Z"
      }
    },
    {
      "description": "Withdrawn from Committee on Rules and referred to calendar of 2-17-2026",
      "date": "2026-02-13T06:00:00+00:00",
      "organization_id": "~{\"classification\": \"lower\"}",
      "classification": [
        "referral"
      ],
      "related_entities": [],
      "_processing": {
        "log_file_created": "2026-07-15T13:15:17Z"
      }
    },
    {
      "description": "Representative Ortiz-Velez added as a coauthor",
      "date": "2026-02-16T06:00:00+00:00",
      "organization_id": "~{\"classification\": \"lower\"}",
      "classification": [],
      "related_entities": [],
      "_processing": {
        "log_file_created": "2026-07-15T13:15:17Z"
      }
    },
    {
      "description": "Read a second time",
      "date": "2026-02-17T06:00:00+00:00",
      "organization_id": "~{\"classification\": \"lower\"}",
      "classification": [
        "reading-2"
      ],
      "related_entities": [],
      "_processing": {
        "log_file_created": "2026-07-15T13:15:17Z"
      }
    },
    {
      "description": "Assembly Amendment 1 adopted",
      "date": "2026-02-17T06:00:00+00:00",
      "organization_id": "~{\"classification\": \"lower\"}",
      "classification": [
        "amendment-passage",
        "passage"
      ],
      "related_entities": [],
      "_processing": {
        "log_file_created": "2026-07-15T13:15:17Z"
      }
    },
    {
      "description": "Assembly Amendment 2 adopted",
      "date": "2026-02-17T06:00:00+00:00",
      "organization_id": "~{\"classification\": \"lower\"}",
      "classification": [
        "amendment-passage",
        "passage"
      ],
      "related_entities": [],
      "_processing": {
        "log_file_created": "2026-07-15T13:15:17Z"
      }
    },
    {
      "description": "Ordered to a third reading",
      "date": "2026-02-17T06:00:00+00:00",
      "organization_id": "~{\"classification\": \"lower\"}",
      "classification": [
        "reading-3"
      ],
      "related_entities": [],
      "_processing": {
        "log_file_created": "2026-07-15T13:15:17Z"
      }
    },
    {
      "description": "Rules suspended",
      "date": "2026-02-17T06:00:00+00:00",
      "organization_id": "~{\"classification\": \"lower\"}",
      "classification": [],
      "related_entities": [],
      "_processing": {
        "log_file_created": "2026-07-15T13:15:17Z"
      }
    },
    {
      "description": "Read a third time and passed, Ayes 85, Noes 14",
      "date": "2026-02-17T06:00:00+00:00",
      "organization_id": "~{\"classification\": \"lower\"}",
      "classification": [
        "passage",
        "reading-3"
      ],
      "related_entities": [],
      "_processing": {
        "log_file_created": "2026-07-15T13:15:17Z"
      }
    },
    {
      "description": "Ordered immediately messaged",
      "date": "2026-02-17T06:00:00+00:00",
      "organization_id": "~{\"classification\": \"lower\"}",
      "classification": [],
      "related_entities": [],
      "_processing": {
        "log_file_created": "2026-07-15T13:15:17Z"
      }
    },
    {
      "description": "Received from Assembly",
      "date": "2026-02-18T06:00:00+00:00",
      "organization_id": "~{\"classification\": \"upper\"}",
      "classification": [
        "receipt"
      ],
      "related_entities": [],
      "_processing": {
        "log_file_created": "2026-07-15T13:15:17Z"
      }
    },
    {
      "description": "Read first time and referred to committee on Judiciary and Public Safety",
      "date": "2026-02-20T06:00:00+00:00",
      "organization_id": "~{\"classification\": \"upper\"}",
      "classification": [
        "reading-1",
        "referral-committee"
      ],
      "related_entities": [],
      "_processing": {
        "log_file_created": "2026-07-15T13:15:17Z"
      }
    },
    {
      "description": "Executive action taken",
      "date": "2026-03-03T06:00:00+00:00",
      "organization_id": "~{\"classification\": \"upper\"}",
      "classification": [],
      "related_entities": [],
      "_processing": {
        "log_file_created": "2026-07-15T13:15:17Z"
      }
    },
    {
      "description": "Report concurrence recommended by Committee on Judiciary and Public Safety, Ayes 8, Noes 0",
      "date": "2026-03-03T06:00:00+00:00",
      "organization_id": "~{\"classification\": \"upper\"}",
      "classification": [
        "committee-passage-favorable"
      ],
      "related_entities": [],
      "_processing": {
        "log_file_created": "2026-07-15T13:15:17Z"
      }
    },
    {
      "description": "Available for scheduling",
      "date": "2026-03-03T06:00:00+00:00",
      "organization_id": "~{\"classification\": \"upper\"}",
      "classification": [],
      "related_entities": [],
      "_processing": {
        "log_file_created": "2026-07-15T13:15:17Z"
      }
    },
    {
      "description": "Public hearing requirement waived by committee on Senate Organization, pursuant to Senate Rule 18 (1m), Ayes 3, Noes 2",
      "date": "2026-03-16T05:00:00+00:00",
      "organization_id": "~{\"classification\": \"upper\"}",
      "classification": [],
      "related_entities": [],
      "_processing": {
        "log_file_created": "2026-07-15T13:15:17Z"
      }
    },
    {
      "description": "Placed on calendar 3-17-2026 pursuant to Senate Rule 18(1)",
      "date": "2026-03-16T05:00:00+00:00",
      "organization_id": "~{\"classification\": \"upper\"}",
      "classification": [],
      "related_entities": [],
      "_processing": {
        "log_file_created": "2026-07-15T13:15:17Z"
      }
    },
    {
      "description": "Read a second time",
      "date": "2026-03-17T05:00:00+00:00",
      "organization_id": "~{\"classification\": \"upper\"}",
      "classification": [
        "reading-2"
      ],
      "related_entities": [],
      "_processing": {
        "log_file_created": "2026-07-15T13:15:17Z"
      }
    },
    {
      "description": "Ordered to a third reading",
      "date": "2026-03-17T05:00:00+00:00",
      "organization_id": "~{\"classification\": \"upper\"}",
      "classification": [
        "reading-3"
      ],
      "related_entities": [],
      "_processing": {
        "log_file_created": "2026-07-15T13:15:17Z"
      }
    },
    {
      "description": "Rules suspended to give bill its third reading",
      "date": "2026-03-17T05:00:00+00:00",
      "organization_id": "~{\"classification\": \"upper\"}",
      "classification": [],
      "related_entities": [],
      "_processing": {
        "log_file_created": "2026-07-15T13:15:17Z"
      }
    },
    {
      "description": "Read a third time and concurred in",
      "date": "2026-03-17T05:00:00+00:00",
      "organization_id": "~{\"classification\": \"upper\"}",
      "classification": [
        "passage",
        "reading-3"
      ],
      "related_entities": [],
      "_processing": {
        "log_file_created": "2026-07-15T13:15:17Z"
      }
    },
    {
      "description": "Senator Smith added as a cosponsor",
      "date": "2026-03-17T05:00:00+00:00",
      "organization_id": "~{\"classification\": \"upper\"}",
      "classification": [],
      "related_entities": [],
      "_processing": {
        "log_file_created": "2026-07-15T13:15:17Z"
      }
    },
    {
      "description": "Ordered immediately messaged",
      "date": "2026-03-17T05:00:00+00:00",
      "organization_id": "~{\"classification\": \"upper\"}",
      "classification": [],
      "related_entities": [],
      "_processing": {
        "log_file_created": "2026-07-15T13:15:17Z"
      }
    },
    {
      "description": "Received from Senate concurred in",
      "date": "2026-03-18T05:00:00+00:00",
      "organization_id": "~{\"classification\": \"lower\"}",
      "classification": [
        "receipt"
      ],
      "related_entities": [],
      "_processing": {
        "log_file_created": "2026-07-15T13:15:17Z"
      }
    },
    {
      "description": "Report correctly enrolled on 3-23-2026",
      "date": "2026-03-23T05:00:00+00:00",
      "organization_id": "~{\"classification\": \"lower\"}",
      "classification": [
        "enrolled"
      ],
      "related_entities": [],
      "_processing": {
        "log_file_created": "2026-07-15T13:15:17Z"
      }
    },
    {
      "description": "Presented to the Governor on 4-2-2026",
      "date": "2026-04-02T05:00:00+00:00",
      "organization_id": "~{\"classification\": \"lower\"}",
      "classification": [
        "executive-receipt"
      ],
      "related_entities": [],
      "_processing": {
        "log_file_created": "2026-07-15T13:15:17Z"
      }
    },
    {
      "description": "Report approved by the Governor on 4-3-2026. 2025 Wisconsin Act 194",
      "date": "2026-04-03T05:00:00+00:00",
      "organization_id": "~{\"classification\": \"lower\"}",
      "classification": [
        "executive-signature"
      ],
      "related_entities": [],
      "_processing": {
        "log_file_created": "2026-07-15T13:15:17Z"
      }
    },
    {
      "description": "Published 4-4-2026",
      "date": "2026-04-03T05:00:00+00:00",
      "organization_id": "~{\"classification\": \"lower\"}",
      "classification": [
        "became-law"
      ],
      "related_entities": [],
      "_processing": {
        "log_file_created": "2026-07-15T13:15:17Z"
      }
    }
  ],
  "sponsorships": [
    {
      "name": "Donovan",
      "classification": "primary",
      "entity_type": "person",
      "primary": true,
      "person_id": "~{\"chamber\": \"lower\", \"name\": \"Donovan\"}",
      "organization_id": null
    },
    {
      "name": "Dittrich",
      "classification": "primary",
      "entity_type": "person",
      "primary": true,
      "person_id": "~{\"chamber\": \"lower\", \"name\": \"Dittrich\"}",
      "organization_id": null
    },
    {
      "name": "Goodwin",
      "classification": "primary",
      "entity_type": "person",
      "primary": true,
      "person_id": "~{\"chamber\": \"lower\", \"name\": \"Goodwin\"}",
      "organization_id": null
    },
    {
      "name": "Knodl",
      "classification": "primary",
      "entity_type": "person",
      "primary": true,
      "person_id": "~{\"chamber\": \"lower\", \"name\": \"Knodl\"}",
      "organization_id": null
    },
    {
      "name": "Maxey",
      "classification": "primary",
      "entity_type": "person",
      "primary": true,
      "person_id": "~{\"chamber\": \"lower\", \"name\": \"Maxey\"}",
      "organization_id": null
    },
    {
      "name": "Melotik",
      "classification": "primary",
      "entity_type": "person",
      "primary": true,
      "person_id": "~{\"chamber\": \"lower\", \"name\": \"Melotik\"}",
      "organization_id": null
    },
    {
      "name": "Murphy",
      "classification": "primary",
      "entity_type": "person",
      "primary": true,
      "person_id": "~{\"chamber\": \"lower\", \"name\": \"Murphy\"}",
      "organization_id": null
    },
    {
      "name": "Novak",
      "classification": "primary",
      "entity_type": "person",
      "primary": true,
      "person_id": "~{\"chamber\": \"lower\", \"name\": \"Novak\"}",
      "organization_id": null
    },
    {
      "name": "O'Connor",
      "classification": "primary",
      "entity_type": "person",
      "primary": true,
      "person_id": "~{\"chamber\": \"lower\", \"name\": \"O'Connor\"}",
      "organization_id": null
    },
    {
      "name": "Penterman",
      "classification": "primary",
      "entity_type": "person",
      "primary": true,
      "person_id": "~{\"chamber\": \"lower\", \"name\": \"Penterman\"}",
      "organization_id": null
    },
    {
      "name": "Sinicki",
      "classification": "primary",
      "entity_type": "person",
      "primary": true,
      "person_id": "~{\"chamber\": \"lower\", \"name\": \"Sinicki\"}",
      "organization_id": null
    },
    {
      "name": "Tittl",
      "classification": "primary",
      "entity_type": "person",
      "primary": true,
      "person_id": "~{\"chamber\": \"lower\", \"name\": \"Tittl\"}",
      "organization_id": null
    },
    {
      "name": "Wichgers",
      "classification": "primary",
      "entity_type": "person",
      "primary": true,
      "person_id": "~{\"chamber\": \"lower\", \"name\": \"Wichgers\"}",
      "organization_id": null
    }
  ],
  "related_bills": [],
  "versions": [
    {
      "note": "Bill Text",
      "links": [
        {
          "url": "https://docs.legis.wisconsin.gov/document/proposaltext/2025/REG/AB768",
          "media_type": "text/html"
        },
        {
          "url": "https://docs.legis.wisconsin.gov/document/proposaltext/2025/REG/AB768.pdf",
          "media_type": "application/pdf"
        }
      ],
      "date": "",
      "classification": ""
    },
    {
      "note": "Assembly Amendment 1",
      "links": [
        {
          "url": "https://docs.legis.wisconsin.gov/document/amends/2025/REG/AB768-AA1",
          "media_type": "text/html"
        },
        {
          "url": "https://docs.legis.wisconsin.gov/document/amends/2025/REG/AB768-AA1.pdf",
          "media_type": "application/pdf"
        }
      ],
      "date": "",
      "classification": ""
    },
    {
      "note": "Assembly Amendment 2",
      "links": [
        {
          "url": "https://docs.legis.wisconsin.gov/document/amends/2025/REG/AB768-AA2",
          "media_type": "text/html"
        },
        {
          "url": "https://docs.legis.wisconsin.gov/document/amends/2025/REG/AB768-AA2.pdf",
          "media_type": "application/pdf"
        }
      ],
      "date": "",
      "classification": ""
    }
  ],
  "documents": [
    {
      "note": "Amendment Histories",
      "links": [
        {
          "url": "https://docs.legis.wisconsin.gov/document/amends/2025/REG/AB768",
          "media_type": "text/html"
        }
      ],
      "date": "",
      "classification": ""
    },
    {
      "note": "2025 Wisconsin Act 194",
      "links": [
        {
          "url": "https://docs.legis.wisconsin.gov/document/acts/2025/194",
          "media_type": ""
        }
      ],
      "date": "",
      "classification": ""
    },
    {
      "note": "2025 Wisconsin Act 194: LC Act Memo",
      "links": [
        {
          "url": "https://docs.legis.wisconsin.gov/document/lcactmemos/2025/REG/Act%20194.pdf",
          "media_type": ""
        }
      ],
      "date": "",
      "classification": ""
    },
    {
      "note": "LC Amendment Memo",
      "links": [
        {
          "url": "https://docs.legis.wisconsin.gov/document/lcamendmentmemos/2025/REG/AB768.pdf",
          "media_type": ""
        }
      ],
      "date": "",
      "classification": ""
    },
    {
      "note": "AB768 ROCP for Committee on Criminal Justice and Public Safety On 1/22/2026",
      "links": [
        {
          "url": "https://docs.legis.wisconsin.gov/2025/related/records/assembly/criminal_justice_and_public_safety/1966750",
          "media_type": "text/html"
        }
      ],
      "date": "",
      "classification": ""
    },
    {
      "note": "AB768 ROCP for Committee on Judiciary and Public Safety On 3/3/2026",
      "links": [
        {
          "url": "https://docs.legis.wisconsin.gov/2025/related/records/senate/judiciary_and_public_safety/1977051",
          "media_type": "text/html"
        }
      ],
      "date": "",
      "classification": ""
    },
    {
      "note": "LC Bill Hearing Materials",
      "links": [
        {
          "url": "https://docs.legis.wisconsin.gov/document/lcbillhearingtestimonyandmaterials/2025/REG/AB768",
          "media_type": "text/html"
        }
      ],
      "date": "",
      "classification": ""
    },
    {
      "note": "Wisconsin Ethics Commission information",
      "links": [
        {
          "url": "https://lobbying.wi.gov/What/BillInformation/2025REG/BillKey/REGAB768",
          "media_type": "text/html"
        }
      ],
      "date": "",
      "classification": ""
    },
    {
      "note": "2025 Senate Bill 766",
      "links": [
        {
          "url": "https://docs.legis.wisconsin.gov/2025/proposals/sb766",
          "media_type": "text/html"
        }
      ],
      "date": "",
      "classification": ""
    }
  ],
  "citations": [],
  "sources": [
    {
      "url": "https://docs.legis.wisconsin.gov/2025/proposals/reg/asm/bill/ab768",
      "note": ""
    }
  ],
  "extras": {
    "status": "Status: A - Enacted into Law"
  },
  "jurisdiction": {
    "id": "ocd-jurisdiction/country:us/state:wi/government",
    "name": "Wisconsin",
    "classification": "state",
    "division_id": "ocd-division/country:us/state:wi"
  },
  "_processing": {
    "logs_latest_update": "2026-07-15T13:15:17Z"
  }
}