{
  "legislative_session": "2025",
  "identifier": "AB943",
  "title": "Relating to: going armed at a polling place and providing a penalty.",
  "from_organization": "~{\"classification\": \"lower\"}",
  "classification": [
    "bill"
  ],
  "subject": [],
  "abstracts": [],
  "other_titles": [],
  "other_identifiers": [
    {
      "identifier": "ocd-bill-wi-2025-ab943"
    }
  ],
  "actions": [
    {
      "description": "Introduced by Representatives Stubbs, Andraca, Kirsch, Udell, Sinicki, Prado, Fitzgerald, Miresse, Roe, Neubauer, Snodgrass, Joers, Arney, J. Jacobson, Stroud and DeSmidt; \ncosponsored by Senators Larson, L. Johnson, Roys, Ratcliff, Spreitzer and Dassler-Alfheim",
      "date": "2026-01-28T06:00:00+00:00",
      "organization_id": "~{\"classification\": \"lower\"}",
      "classification": [
        "introduction"
      ],
      "related_entities": [],
      "_processing": {
        "log_file_created": "2026-07-15T13:15:15Z"
      }
    },
    {
      "description": "Read first time and referred to Committee on Campaigns and Elections",
      "date": "2026-01-28T06:00:00+00:00",
      "organization_id": "~{\"classification\": \"lower\"}",
      "classification": [
        "reading-1",
        "referral-committee"
      ],
      "related_entities": [],
      "_processing": {
        "log_file_created": "2026-07-15T13:15:15Z"
      }
    },
    {
      "description": "Representative Sheehan added as a coauthor",
      "date": "2026-02-20T06:00:00+00:00",
      "organization_id": "~{\"classification\": \"lower\"}",
      "classification": [],
      "related_entities": [],
      "_processing": {
        "log_file_created": "2026-07-15T13:15:15Z"
      }
    },
    {
      "description": "Representative Subeck added as a coauthor",
      "date": "2026-02-26T06:00:00+00:00",
      "organization_id": "~{\"classification\": \"lower\"}",
      "classification": [],
      "related_entities": [],
      "_processing": {
        "log_file_created": "2026-07-15T13:15:15Z"
      }
    },
    {
      "description": "Failed to pass pursuant to Senate Joint Resolution 1",
      "date": "2026-03-23T05:00:00+00:00",
      "organization_id": "~{\"classification\": \"lower\"}",
      "classification": [
        "failure"
      ],
      "related_entities": [],
      "_processing": {
        "log_file_created": "2026-07-15T13:15:15Z"
      }
    },
    {
      "description": "Representative Mayadev added as a coauthor",
      "date": "2026-04-21T05:00:00+00:00",
      "organization_id": "~{\"classification\": \"lower\"}",
      "classification": [],
      "related_entities": [],
      "_processing": {
        "log_file_created": "2026-07-15T13:15:15Z"
      }
    }
  ],
  "sponsorships": [
    {
      "name": "Stubbs",
      "classification": "primary",
      "entity_type": "person",
      "primary": true,
      "person_id": "~{\"chamber\": \"lower\", \"name\": \"Stubbs\"}",
      "organization_id": null
    },
    {
      "name": "Andraca",
      "classification": "primary",
      "entity_type": "person",
      "primary": true,
      "person_id": "~{\"chamber\": \"lower\", \"name\": \"Andraca\"}",
      "organization_id": null
    },
    {
      "name": "Kirsch",
      "classification": "primary",
      "entity_type": "person",
      "primary": true,
      "person_id": "~{\"chamber\": \"lower\", \"name\": \"Kirsch\"}",
      "organization_id": null
    },
    {
      "name": "Udell",
      "classification": "primary",
      "entity_type": "person",
      "primary": true,
      "person_id": "~{\"chamber\": \"lower\", \"name\": \"Udell\"}",
      "organization_id": null
    },
    {
      "name": "Sinicki",
      "classification": "primary",
      "entity_type": "person",
      "primary": true,
      "person_id": "~{\"chamber\": \"lower\", \"name\": \"Sinicki\"}",
      "organization_id": null
    },
    {
      "name": "Prado",
      "classification": "primary",
      "entity_type": "person",
      "primary": true,
      "person_id": "~{\"chamber\": \"lower\", \"name\": \"Prado\"}",
      "organization_id": null
    },
    {
      "name": "Fitzgerald",
      "classification": "primary",
      "entity_type": "person",
      "primary": true,
      "person_id": "~{\"chamber\": \"lower\", \"name\": \"Fitzgerald\"}",
      "organization_id": null
    },
    {
      "name": "Miresse",
      "classification": "primary",
      "entity_type": "person",
      "primary": true,
      "person_id": "~{\"chamber\": \"lower\", \"name\": \"Miresse\"}",
      "organization_id": null
    },
    {
      "name": "Roe",
      "classification": "primary",
      "entity_type": "person",
      "primary": true,
      "person_id": "~{\"chamber\": \"lower\", \"name\": \"Roe\"}",
      "organization_id": null
    },
    {
      "name": "Neubauer",
      "classification": "primary",
      "entity_type": "person",
      "primary": true,
      "person_id": "~{\"chamber\": \"lower\", \"name\": \"Neubauer\"}",
      "organization_id": null
    },
    {
      "name": "Snodgrass",
      "classification": "primary",
      "entity_type": "person",
      "primary": true,
      "person_id": "~{\"chamber\": \"lower\", \"name\": \"Snodgrass\"}",
      "organization_id": null
    },
    {
      "name": "Joers",
      "classification": "primary",
      "entity_type": "person",
      "primary": true,
      "person_id": "~{\"chamber\": \"lower\", \"name\": \"Joers\"}",
      "organization_id": null
    },
    {
      "name": "Arney",
      "classification": "primary",
      "entity_type": "person",
      "primary": true,
      "person_id": "~{\"chamber\": \"lower\", \"name\": \"Arney\"}",
      "organization_id": null
    },
    {
      "name": "J. Jacobson",
      "classification": "primary",
      "entity_type": "person",
      "primary": true,
      "person_id": "~{\"chamber\": \"lower\", \"name\": \"J. Jacobson\"}",
      "organization_id": null
    },
    {
      "name": "Stroud",
      "classification": "primary",
      "entity_type": "person",
      "primary": true,
      "person_id": "~{\"chamber\": \"lower\", \"name\": \"Stroud\"}",
      "organization_id": null
    },
    {
      "name": "DeSmidt",
      "classification": "primary",
      "entity_type": "person",
      "primary": true,
      "person_id": "~{\"chamber\": \"lower\", \"name\": \"DeSmidt\"}",
      "organization_id": null
    }
  ],
  "related_bills": [],
  "versions": [
    {
      "note": "Bill Text",
      "links": [
        {
          "url": "https://docs.legis.wisconsin.gov/document/proposaltext/2025/REG/AB943",
          "media_type": "text/html"
        },
        {
          "url": "https://docs.legis.wisconsin.gov/document/proposaltext/2025/REG/AB943.pdf",
          "media_type": "application/pdf"
        }
      ],
      "date": "",
      "classification": ""
    }
  ],
  "documents": [
    {
      "note": "AB943 ROCP for Committee on Campaigns and Elections",
      "links": [
        {
          "url": "https://docs.legis.wisconsin.gov/2025/related/records/assembly/campaigns_and_elections/1984488",
          "media_type": "text/html"
        }
      ],
      "date": "",
      "classification": ""
    },
    {
      "note": "Wisconsin Ethics Commission information",
      "links": [
        {
          "url": "https://lobbying.wi.gov/What/BillInformation/2025REG/BillKey/REGAB943",
          "media_type": "text/html"
        }
      ],
      "date": "",
      "classification": ""
    },
    {
      "note": "2025 Senate Bill 949",
      "links": [
        {
          "url": "https://docs.legis.wisconsin.gov/2025/proposals/sb949",
          "media_type": "text/html"
        }
      ],
      "date": "",
      "classification": ""
    }
  ],
  "citations": [],
  "sources": [
    {
      "url": "https://docs.legis.wisconsin.gov/2025/proposals/reg/asm/bill/ab943",
      "note": ""
    }
  ],
  "extras": {
    "status": "Status: A - Campaigns and Elections"
  },
  "jurisdiction": {
    "id": "ocd-jurisdiction/country:us/state:wi/government",
    "name": "Wisconsin",
    "classification": "state",
    "division_id": "ocd-division/country:us/state:wi"
  },
  "_processing": {
    "logs_latest_update": "2026-07-15T13:15:15Z",
    "text_extraction_latest_update": "2026-07-15T15:41:40.186568Z"
  }
}