{
  "legislative_session": "2025",
  "identifier": "AB650",
  "title": "Relating to: funding for identity verification under the unemployment insurance law and making an appropriation. (FE)",
  "from_organization": "~{\"classification\": \"lower\"}",
  "classification": [
    "bill"
  ],
  "subject": [],
  "abstracts": [],
  "other_titles": [],
  "other_identifiers": [
    {
      "identifier": "ocd-bill-wi-2025-ab650"
    }
  ],
  "actions": [
    {
      "description": "Introduced by Committee on Workforce Development, Labor, and Integrated Employment",
      "date": "2025-11-13T06:00:00+00:00",
      "organization_id": "~{\"classification\": \"lower\"}",
      "classification": [
        "introduction"
      ],
      "related_entities": [],
      "_processing": {
        "log_file_created": "2026-07-13T06:07:43Z"
      }
    },
    {
      "description": "Read first time and referred to Committee on Workforce Development, Labor, and Integrated Employment",
      "date": "2025-11-13T06:00:00+00:00",
      "organization_id": "~{\"classification\": \"lower\"}",
      "classification": [
        "reading-1",
        "referral-committee"
      ],
      "related_entities": [],
      "_processing": {
        "log_file_created": "2026-07-13T06:07:43Z"
      }
    },
    {
      "description": "Public hearing held",
      "date": "2025-11-13T06:00:00+00:00",
      "organization_id": "~{\"classification\": \"lower\"}",
      "classification": [],
      "related_entities": [],
      "_processing": {
        "log_file_created": "2026-07-13T06:07:43Z"
      }
    },
    {
      "description": "Assembly Amendment 1 offered by Representative Melotik",
      "date": "2025-12-29T06:00:00+00:00",
      "organization_id": "~{\"classification\": \"lower\"}",
      "classification": [
        "amendment-introduction"
      ],
      "related_entities": [],
      "_processing": {
        "log_file_created": "2026-07-15T13:15:16Z"
      }
    },
    {
      "description": "Executive action taken",
      "date": "2026-01-06T06:00:00+00:00",
      "organization_id": "~{\"classification\": \"lower\"}",
      "classification": [],
      "related_entities": [],
      "_processing": {
        "log_file_created": "2026-07-15T13:15:16Z"
      }
    },
    {
      "description": "Report Assembly Amendment 1 adoption recommended by Committee on Workforce Development, Labor, and Integrated Employment, Ayes 9, Noes 0",
      "date": "2026-01-06T06:00:00+00:00",
      "organization_id": "~{\"classification\": \"lower\"}",
      "classification": [
        "committee-passage-favorable"
      ],
      "related_entities": [],
      "_processing": {
        "log_file_created": "2026-07-15T13:15:16Z"
      }
    },
    {
      "description": "Report passage as amended recommended by Committee on Workforce Development, Labor, and Integrated Employment, Ayes 9, Noes 0",
      "date": "2026-01-06T06:00:00+00:00",
      "organization_id": "~{\"classification\": \"lower\"}",
      "classification": [
        "committee-passage-favorable"
      ],
      "related_entities": [],
      "_processing": {
        "log_file_created": "2026-07-15T13:15:16Z"
      }
    },
    {
      "description": "Referred to committee on Rules",
      "date": "2026-01-06T06:00:00+00:00",
      "organization_id": "~{\"classification\": \"lower\"}",
      "classification": [
        "referral-committee"
      ],
      "related_entities": [],
      "_processing": {
        "log_file_created": "2026-07-15T13:15:16Z"
      }
    },
    {
      "description": "Withdrawn from committee on Rules and referred to joint committee on Finance pursuant to Assembly Rule 24 (3)(a)",
      "date": "2026-01-13T06:00:00+00:00",
      "organization_id": "~{\"classification\": \"lower\"}",
      "classification": [
        "referral-committee"
      ],
      "related_entities": [],
      "_processing": {
        "log_file_created": "2026-07-15T13:15:16Z"
      }
    },
    {
      "description": "Assembly Amendment 1 to Assembly Amendment 1 offered by Joint Committee on Finance",
      "date": "2026-01-14T06:00:00+00:00",
      "organization_id": "~{\"classification\": \"lower\"}",
      "classification": [
        "amendment-introduction"
      ],
      "related_entities": [],
      "_processing": {
        "log_file_created": "2026-07-15T13:15:16Z"
      }
    },
    {
      "description": "Executive action taken by joint committee on Finance",
      "date": "2026-01-14T06:00:00+00:00",
      "organization_id": "~{\"classification\": \"lower\"}",
      "classification": [],
      "related_entities": [],
      "_processing": {
        "log_file_created": "2026-07-15T13:15:16Z"
      }
    },
    {
      "description": "Report Assembly Amendment 1 to Assembly Amendment 1 adoption recommended by Joint Committee on Finance, Ayes 16, Noes 0",
      "date": "2026-01-14T06:00:00+00:00",
      "organization_id": "~{\"classification\": \"lower\"}",
      "classification": [
        "committee-passage-favorable"
      ],
      "related_entities": [],
      "_processing": {
        "log_file_created": "2026-07-15T13:15:16Z"
      }
    },
    {
      "description": "Report Assembly Amendment 1 adoption recommended by Joint Committee on Finance, Ayes 16, Noes 0",
      "date": "2026-01-14T06:00:00+00:00",
      "organization_id": "~{\"classification\": \"lower\"}",
      "classification": [
        "committee-passage-favorable"
      ],
      "related_entities": [],
      "_processing": {
        "log_file_created": "2026-07-15T13:15:16Z"
      }
    },
    {
      "description": "Report passage as amended recommended by Joint Committee on Finance, Ayes 16, Noes 0",
      "date": "2026-01-14T06:00:00+00:00",
      "organization_id": "~{\"classification\": \"lower\"}",
      "classification": [
        "committee-passage-favorable"
      ],
      "related_entities": [],
      "_processing": {
        "log_file_created": "2026-07-15T13:15:16Z"
      }
    },
    {
      "description": "Referred to committee on Rules",
      "date": "2026-01-14T06:00:00+00:00",
      "organization_id": "~{\"classification\": \"lower\"}",
      "classification": [
        "referral-committee"
      ],
      "related_entities": [],
      "_processing": {
        "log_file_created": "2026-07-15T13:15:16Z"
      }
    },
    {
      "description": "Placed on calendar 1-20-2026 by Committee on Rules",
      "date": "2026-01-14T06:00:00+00:00",
      "organization_id": "~{\"classification\": \"lower\"}",
      "classification": [],
      "related_entities": [],
      "_processing": {
        "log_file_created": "2026-07-15T13:15:16Z"
      }
    },
    {
      "description": "Read a second time",
      "date": "2026-01-20T06:00:00+00:00",
      "organization_id": "~{\"classification\": \"lower\"}",
      "classification": [
        "reading-2"
      ],
      "related_entities": [],
      "_processing": {
        "log_file_created": "2026-07-15T13:15:16Z"
      }
    },
    {
      "description": "Assembly Amendment 1 to Assembly Amendment 1 adopted",
      "date": "2026-01-20T06:00:00+00:00",
      "organization_id": "~{\"classification\": \"lower\"}",
      "classification": [
        "amendment-passage",
        "passage"
      ],
      "related_entities": [],
      "_processing": {
        "log_file_created": "2026-07-15T13:15:16Z"
      }
    },
    {
      "description": "Assembly Amendment 1 adopted",
      "date": "2026-01-20T06:00:00+00:00",
      "organization_id": "~{\"classification\": \"lower\"}",
      "classification": [
        "amendment-passage",
        "passage"
      ],
      "related_entities": [],
      "_processing": {
        "log_file_created": "2026-07-15T13:15:16Z"
      }
    },
    {
      "description": "Ordered to a third reading",
      "date": "2026-01-20T06:00:00+00:00",
      "organization_id": "~{\"classification\": \"lower\"}",
      "classification": [
        "reading-3"
      ],
      "related_entities": [],
      "_processing": {
        "log_file_created": "2026-07-15T13:15:16Z"
      }
    },
    {
      "description": "Rules suspended",
      "date": "2026-01-20T06:00:00+00:00",
      "organization_id": "~{\"classification\": \"lower\"}",
      "classification": [],
      "related_entities": [],
      "_processing": {
        "log_file_created": "2026-07-15T13:15:16Z"
      }
    },
    {
      "description": "Read a third time and passed, Ayes 97, Noes 0",
      "date": "2026-01-20T06:00:00+00:00",
      "organization_id": "~{\"classification\": \"lower\"}",
      "classification": [
        "passage",
        "reading-3"
      ],
      "related_entities": [],
      "_processing": {
        "log_file_created": "2026-07-15T13:15:16Z"
      }
    },
    {
      "description": "Ordered immediately messaged",
      "date": "2026-01-20T06:00:00+00:00",
      "organization_id": "~{\"classification\": \"lower\"}",
      "classification": [],
      "related_entities": [],
      "_processing": {
        "log_file_created": "2026-07-15T13:15:16Z"
      }
    },
    {
      "description": "Received from Assembly",
      "date": "2026-01-20T06:00:00+00:00",
      "organization_id": "~{\"classification\": \"upper\"}",
      "classification": [
        "receipt"
      ],
      "related_entities": [],
      "_processing": {
        "log_file_created": "2026-07-15T13:15:16Z"
      }
    },
    {
      "description": "Fiscal estimate received",
      "date": "2026-01-22T06:00:00+00:00",
      "organization_id": "~{\"classification\": \"upper\"}",
      "classification": [
        "receipt"
      ],
      "related_entities": [],
      "_processing": {
        "log_file_created": "2026-07-15T13:15:16Z"
      }
    },
    {
      "description": "Read first time and referred to committee on Senate Organization",
      "date": "2026-01-23T06:00:00+00:00",
      "organization_id": "~{\"classification\": \"upper\"}",
      "classification": [
        "reading-1",
        "referral-committee"
      ],
      "related_entities": [],
      "_processing": {
        "log_file_created": "2026-07-15T13:15:16Z"
      }
    },
    {
      "description": "Available for scheduling",
      "date": "2026-01-23T06:00:00+00:00",
      "organization_id": "~{\"classification\": \"upper\"}",
      "classification": [],
      "related_entities": [],
      "_processing": {
        "log_file_created": "2026-07-15T13:15:16Z"
      }
    },
    {
      "description": "Public hearing requirement waived by committee on Senate Organization, pursuant to Senate Rule 18 (1m), Ayes 3, Noes 2",
      "date": "2026-03-16T05:00:00+00:00",
      "organization_id": "~{\"classification\": \"upper\"}",
      "classification": [],
      "related_entities": [],
      "_processing": {
        "log_file_created": "2026-07-15T13:15:16Z"
      }
    },
    {
      "description": "Placed on calendar 3-17-2026 pursuant to Senate Rule 18(1)",
      "date": "2026-03-16T05:00:00+00:00",
      "organization_id": "~{\"classification\": \"upper\"}",
      "classification": [],
      "related_entities": [],
      "_processing": {
        "log_file_created": "2026-07-15T13:15:16Z"
      }
    },
    {
      "description": "Read a second time",
      "date": "2026-03-17T05:00:00+00:00",
      "organization_id": "~{\"classification\": \"upper\"}",
      "classification": [
        "reading-2"
      ],
      "related_entities": [],
      "_processing": {
        "log_file_created": "2026-07-15T13:15:16Z"
      }
    },
    {
      "description": "Ordered to a third reading",
      "date": "2026-03-17T05:00:00+00:00",
      "organization_id": "~{\"classification\": \"upper\"}",
      "classification": [
        "reading-3"
      ],
      "related_entities": [],
      "_processing": {
        "log_file_created": "2026-07-15T13:15:16Z"
      }
    },
    {
      "description": "Rules suspended to give bill its third reading",
      "date": "2026-03-17T05:00:00+00:00",
      "organization_id": "~{\"classification\": \"upper\"}",
      "classification": [],
      "related_entities": [],
      "_processing": {
        "log_file_created": "2026-07-15T13:15:16Z"
      }
    },
    {
      "description": "Read a third time and concurred in, Ayes 33, Noes 0",
      "date": "2026-03-17T05:00:00+00:00",
      "organization_id": "~{\"classification\": \"upper\"}",
      "classification": [
        "passage",
        "reading-3"
      ],
      "related_entities": [],
      "_processing": {
        "log_file_created": "2026-07-15T13:15:16Z"
      }
    },
    {
      "description": "Senator Smith added as a cosponsor",
      "date": "2026-03-17T05:00:00+00:00",
      "organization_id": "~{\"classification\": \"upper\"}",
      "classification": [],
      "related_entities": [],
      "_processing": {
        "log_file_created": "2026-07-15T13:15:16Z"
      }
    },
    {
      "description": "Ordered immediately messaged",
      "date": "2026-03-17T05:00:00+00:00",
      "organization_id": "~{\"classification\": \"upper\"}",
      "classification": [],
      "related_entities": [],
      "_processing": {
        "log_file_created": "2026-07-15T13:15:16Z"
      }
    },
    {
      "description": "Received from Senate concurred in",
      "date": "2026-03-18T05:00:00+00:00",
      "organization_id": "~{\"classification\": \"lower\"}",
      "classification": [
        "receipt"
      ],
      "related_entities": [],
      "_processing": {
        "log_file_created": "2026-07-15T13:15:16Z"
      }
    },
    {
      "description": "Report correctly enrolled on 3-24-2026",
      "date": "2026-03-24T05:00:00+00:00",
      "organization_id": "~{\"classification\": \"lower\"}",
      "classification": [
        "enrolled"
      ],
      "related_entities": [],
      "_processing": {
        "log_file_created": "2026-07-15T13:15:16Z"
      }
    },
    {
      "description": "Presented to the Governor on 3-26-2026",
      "date": "2026-03-26T05:00:00+00:00",
      "organization_id": "~{\"classification\": \"lower\"}",
      "classification": [
        "executive-receipt"
      ],
      "related_entities": [],
      "_processing": {
        "log_file_created": "2026-07-15T13:15:16Z"
      }
    },
    {
      "description": "Report approved by the Governor with partial veto on 3-30-2026. 2025 Wisconsin Act 144",
      "date": "2026-03-30T05:00:00+00:00",
      "organization_id": "~{\"classification\": \"lower\"}",
      "classification": [
        "executive-veto-line-item"
      ],
      "related_entities": [],
      "_processing": {
        "log_file_created": "2026-07-15T13:15:16Z"
      }
    },
    {
      "description": "Published 3-31-2026",
      "date": "2026-03-30T05:00:00+00:00",
      "organization_id": "~{\"classification\": \"lower\"}",
      "classification": [
        "became-law"
      ],
      "related_entities": [],
      "_processing": {
        "log_file_created": "2026-07-15T13:15:16Z"
      }
    },
    {
      "description": "Partial veto placed on calendar 5-12-2026 pursuant to Joint Rule 82 (2)(a)",
      "date": "2026-05-12T05:00:00+00:00",
      "organization_id": "~{\"classification\": \"lower\"}",
      "classification": [],
      "related_entities": [],
      "_processing": {
        "log_file_created": "2026-07-15T13:15:16Z"
      }
    },
    {
      "description": "Partial veto failed to pass notwithstanding the objections of the Governor pursuant to Joint Rule 82",
      "date": "2026-05-13T05:00:00+00:00",
      "organization_id": "~{\"classification\": \"lower\"}",
      "classification": [
        "failure"
      ],
      "related_entities": [],
      "_processing": {
        "log_file_created": "2026-07-15T13:15:16Z"
      }
    }
  ],
  "sponsorships": [],
  "related_bills": [],
  "versions": [
    {
      "note": "Bill Text",
      "links": [
        {
          "url": "https://docs.legis.wisconsin.gov/document/proposaltext/2025/REG/AB650",
          "media_type": "text/html"
        },
        {
          "url": "https://docs.legis.wisconsin.gov/document/proposaltext/2025/REG/AB650.pdf",
          "media_type": "application/pdf"
        }
      ],
      "date": "",
      "classification": ""
    },
    {
      "note": "Assembly Amendment 1",
      "links": [
        {
          "url": "https://docs.legis.wisconsin.gov/document/amends/2025/REG/AB650-AA1-AA1",
          "media_type": "text/html"
        },
        {
          "url": "https://docs.legis.wisconsin.gov/document/amends/2025/REG/AB650-AA1-AA1.pdf",
          "media_type": "application/pdf"
        },
        {
          "url": "https://docs.legis.wisconsin.gov/document/amends/2025/REG/AB650-AA1",
          "media_type": "text/html"
        },
        {
          "url": "https://docs.legis.wisconsin.gov/document/amends/2025/REG/AB650-AA1.pdf",
          "media_type": "application/pdf"
        }
      ],
      "date": "",
      "classification": ""
    }
  ],
  "documents": [
    {
      "note": "Amendment Histories",
      "links": [
        {
          "url": "https://docs.legis.wisconsin.gov/document/amends/2025/REG/AB650",
          "media_type": "text/html"
        }
      ],
      "date": "",
      "classification": ""
    },
    {
      "note": "2025 Wisconsin Act 144",
      "links": [
        {
          "url": "https://docs.legis.wisconsin.gov/document/acts/2025/144",
          "media_type": ""
        }
      ],
      "date": "",
      "classification": ""
    },
    {
      "note": "2025 Wisconsin Act 144: Veto Message",
      "links": [
        {
          "url": "https://docs.legis.wisconsin.gov/document/vetomessages/2025/AB650.pdf",
          "media_type": ""
        }
      ],
      "date": "",
      "classification": ""
    },
    {
      "note": "2025 Wisconsin Act 144: LC Act Memo",
      "links": [
        {
          "url": "https://docs.legis.wisconsin.gov/document/lcactmemos/2025/REG/Act%20144.pdf",
          "media_type": ""
        }
      ],
      "date": "",
      "classification": ""
    },
    {
      "note": "LC Amendment Memo",
      "links": [
        {
          "url": "https://docs.legis.wisconsin.gov/document/lcamendmentmemos/2025/REG/AB650.pdf",
          "media_type": ""
        }
      ],
      "date": "",
      "classification": ""
    },
    {
      "note": "AB650: Fiscal Estimate From DWD",
      "links": [
        {
          "url": "https://docs.legis.wisconsin.gov/2025/related/fe/ab650/ab650_dwd.pdf",
          "media_type": ""
        }
      ],
      "date": "",
      "classification": ""
    },
    {
      "note": "AB650 ROCP for Committee on Workforce Development, Labor, and Integrated Employment On 1/6/2026",
      "links": [
        {
          "url": "https://docs.legis.wisconsin.gov/2025/related/records/assembly/workforce_development_labor_and_integrated_employment/1954336",
          "media_type": "text/html"
        }
      ],
      "date": "",
      "classification": ""
    },
    {
      "note": "LC Bill Hearing Materials",
      "links": [
        {
          "url": "https://docs.legis.wisconsin.gov/document/lcbillhearingtestimonyandmaterials/2025/REG/AB650",
          "media_type": "text/html"
        }
      ],
      "date": "",
      "classification": ""
    },
    {
      "note": "Wisconsin Ethics Commission information",
      "links": [
        {
          "url": "https://lobbying.wi.gov/What/BillInformation/2025REG/BillKey/REGAB650",
          "media_type": "text/html"
        }
      ],
      "date": "",
      "classification": ""
    },
    {
      "note": "2025 Senate Bill 675",
      "links": [
        {
          "url": "https://docs.legis.wisconsin.gov/2025/proposals/sb675",
          "media_type": "text/html"
        }
      ],
      "date": "",
      "classification": ""
    }
  ],
  "citations": [],
  "sources": [
    {
      "url": "https://docs.legis.wisconsin.gov/2025/proposals/reg/asm/bill/ab650",
      "note": ""
    }
  ],
  "extras": {
    "status": "Status: A - Enacted into Law"
  },
  "jurisdiction": {
    "id": "ocd-jurisdiction/country:us/state:wi/government",
    "name": "Wisconsin",
    "classification": "state",
    "division_id": "ocd-division/country:us/state:wi"
  },
  "_processing": {
    "logs_latest_update": "2026-07-15T13:15:16Z",
    "text_extraction_latest_update": "2026-07-13T08:38:04.155282Z"
  }
}