{
  "action": {
    "description": "Introduced by Senators Keyeski, Larson, Carpenter, Hesselbein, Dassler-Alfheim, Ratcliff, Roys and Spreitzer; \ncosponsored by Representatives Fitzgerald, Sheehan, Neubauer, Anderson, Clancy, DeSmidt, Joers, Johnson, Kirsch, Madison, Miresse, Roe, Sinicki, Tenorio and Udell",
    "occurred_at": "2025-10-30T05:00:00+00:00",
    "jurisdiction_id": "~{\"classification\": \"upper\"}",
    "session_id": "2025",
    "entity_type": "bill",
    "classifications": [
      "introduction"
    ],
    "related_entities": [],
    "sources": [
      {
        "url": "https://docs.legis.wisconsin.gov/2025/proposals/reg/sen/bill/sb604",
        "note": ""
      }
    ]
  },
  "bill_id": "SB604"
}