{
  "legislative_session": "2025",
  "identifier": "AB1093",
  "title": "Relating to: employment by a former member of the legislature as a lobbyist.",
  "from_organization": "~{\"classification\": \"lower\"}",
  "classification": [
    "bill"
  ],
  "subject": [],
  "abstracts": [],
  "other_titles": [],
  "other_identifiers": [
    {
      "identifier": "ocd-bill-wi-2025-ab1093"
    }
  ],
  "actions": [
    {
      "description": "Introduced by Representatives Bare, Emerson, Arney, DeSanto, J. Jacobson, Kaufert, Moore Omokunde, Neubauer, Roe, Sheehan, Snodgrass, Stroud, Tenorio, Tusler and Udell; \ncosponsored by Senators Keyeski, Hesselbein, Larson and Spreitzer",
      "date": "2026-03-13T05:00:00+00:00",
      "organization_id": "~{\"classification\": \"lower\"}",
      "classification": [
        "introduction"
      ],
      "related_entities": [],
      "_processing": {
        "log_file_created": "2026-07-15T13:15:16Z"
      }
    },
    {
      "description": "Read first time and referred to Committee on State Affairs",
      "date": "2026-03-13T05:00:00+00:00",
      "organization_id": "~{\"classification\": \"lower\"}",
      "classification": [
        "reading-1",
        "referral-committee"
      ],
      "related_entities": [],
      "_processing": {
        "log_file_created": "2026-07-15T13:15:16Z"
      }
    },
    {
      "description": "Failed to pass pursuant to Senate Joint Resolution 1",
      "date": "2026-03-23T05:00:00+00:00",
      "organization_id": "~{\"classification\": \"lower\"}",
      "classification": [
        "failure"
      ],
      "related_entities": [],
      "_processing": {
        "log_file_created": "2026-07-15T13:15:16Z"
      }
    }
  ],
  "sponsorships": [
    {
      "name": "Bare",
      "classification": "primary",
      "entity_type": "person",
      "primary": true,
      "person_id": "~{\"chamber\": \"lower\", \"name\": \"Bare\"}",
      "organization_id": null
    },
    {
      "name": "Emerson",
      "classification": "primary",
      "entity_type": "person",
      "primary": true,
      "person_id": "~{\"chamber\": \"lower\", \"name\": \"Emerson\"}",
      "organization_id": null
    },
    {
      "name": "Arney",
      "classification": "primary",
      "entity_type": "person",
      "primary": true,
      "person_id": "~{\"chamber\": \"lower\", \"name\": \"Arney\"}",
      "organization_id": null
    },
    {
      "name": "DeSanto",
      "classification": "primary",
      "entity_type": "person",
      "primary": true,
      "person_id": "~{\"chamber\": \"lower\", \"name\": \"DeSanto\"}",
      "organization_id": null
    },
    {
      "name": "J. Jacobson",
      "classification": "primary",
      "entity_type": "person",
      "primary": true,
      "person_id": "~{\"chamber\": \"lower\", \"name\": \"J. Jacobson\"}",
      "organization_id": null
    },
    {
      "name": "Kaufert",
      "classification": "primary",
      "entity_type": "person",
      "primary": true,
      "person_id": "~{\"chamber\": \"lower\", \"name\": \"Kaufert\"}",
      "organization_id": null
    },
    {
      "name": "Moore Omokunde",
      "classification": "primary",
      "entity_type": "person",
      "primary": true,
      "person_id": "~{\"chamber\": \"lower\", \"name\": \"Moore Omokunde\"}",
      "organization_id": null
    },
    {
      "name": "Neubauer",
      "classification": "primary",
      "entity_type": "person",
      "primary": true,
      "person_id": "~{\"chamber\": \"lower\", \"name\": \"Neubauer\"}",
      "organization_id": null
    },
    {
      "name": "Roe",
      "classification": "primary",
      "entity_type": "person",
      "primary": true,
      "person_id": "~{\"chamber\": \"lower\", \"name\": \"Roe\"}",
      "organization_id": null
    },
    {
      "name": "Sheehan",
      "classification": "primary",
      "entity_type": "person",
      "primary": true,
      "person_id": "~{\"chamber\": \"lower\", \"name\": \"Sheehan\"}",
      "organization_id": null
    },
    {
      "name": "Snodgrass",
      "classification": "primary",
      "entity_type": "person",
      "primary": true,
      "person_id": "~{\"chamber\": \"lower\", \"name\": \"Snodgrass\"}",
      "organization_id": null
    },
    {
      "name": "Stroud",
      "classification": "primary",
      "entity_type": "person",
      "primary": true,
      "person_id": "~{\"chamber\": \"lower\", \"name\": \"Stroud\"}",
      "organization_id": null
    },
    {
      "name": "Tenorio",
      "classification": "primary",
      "entity_type": "person",
      "primary": true,
      "person_id": "~{\"chamber\": \"lower\", \"name\": \"Tenorio\"}",
      "organization_id": null
    },
    {
      "name": "Tusler",
      "classification": "primary",
      "entity_type": "person",
      "primary": true,
      "person_id": "~{\"chamber\": \"lower\", \"name\": \"Tusler\"}",
      "organization_id": null
    },
    {
      "name": "Udell",
      "classification": "primary",
      "entity_type": "person",
      "primary": true,
      "person_id": "~{\"chamber\": \"lower\", \"name\": \"Udell\"}",
      "organization_id": null
    }
  ],
  "related_bills": [],
  "versions": [
    {
      "note": "Bill Text",
      "links": [
        {
          "url": "https://docs.legis.wisconsin.gov/document/proposaltext/2025/REG/AB1093",
          "media_type": "text/html"
        },
        {
          "url": "https://docs.legis.wisconsin.gov/document/proposaltext/2025/REG/AB1093.pdf",
          "media_type": "application/pdf"
        }
      ],
      "date": "",
      "classification": ""
    }
  ],
  "documents": [
    {
      "note": "AB1093 ROCP for Committee on State Affairs",
      "links": [
        {
          "url": "https://docs.legis.wisconsin.gov/2025/related/records/assembly/state_affairs/1989734",
          "media_type": "text/html"
        }
      ],
      "date": "",
      "classification": ""
    },
    {
      "note": "Wisconsin Ethics Commission information",
      "links": [
        {
          "url": "https://lobbying.wi.gov/What/BillInformation/2025REG/BillKey/REGAB1093",
          "media_type": "text/html"
        }
      ],
      "date": "",
      "classification": ""
    },
    {
      "note": "2025 Senate Bill 1035",
      "links": [
        {
          "url": "https://docs.legis.wisconsin.gov/2025/proposals/sb1035",
          "media_type": "text/html"
        }
      ],
      "date": "",
      "classification": ""
    }
  ],
  "citations": [],
  "sources": [
    {
      "url": "https://docs.legis.wisconsin.gov/2025/proposals/reg/asm/bill/ab1093",
      "note": ""
    }
  ],
  "extras": {
    "status": "Status: A - State Affairs"
  },
  "jurisdiction": {
    "id": "ocd-jurisdiction/country:us/state:wi/government",
    "name": "Wisconsin",
    "classification": "state",
    "division_id": "ocd-division/country:us/state:wi"
  },
  "_processing": {
    "logs_latest_update": "2026-07-15T13:15:16Z",
    "text_extraction_latest_update": "2026-07-15T15:42:46.233655Z"
  }
}