{
  "legislative_session": "2025",
  "identifier": "SB867",
  "title": "Relating to: grants for planting trees to address urban heat islands, eligible recipients for urban forestry grants, providing an exemption from emergency rule procedures, and making an appropriation. (FE)",
  "from_organization": "~{\"classification\": \"upper\"}",
  "classification": [
    "bill"
  ],
  "subject": [],
  "abstracts": [],
  "other_titles": [],
  "other_identifiers": [
    {
      "identifier": "ocd-bill-wi-2025-sb867"
    }
  ],
  "actions": [
    {
      "description": "Introduced by Senators Drake, Carpenter, Hesselbein, L. Johnson, Larson, Roys, Smith and Wall; \ncosponsored by Representatives Tenorio, Subeck, Arney, Bare, Goodwin, Hong, Joers, Madison, Miresse, Moore Omokunde, Neubauer, Palmeri, Prado, Sheehan, Sinicki, Stroud, Udell and Vining",
      "date": "2026-01-23T06:00:00+00:00",
      "organization_id": "~{\"classification\": \"upper\"}",
      "classification": [
        "introduction"
      ],
      "related_entities": [],
      "_processing": {
        "log_file_created": "2026-07-15T13:15:14Z"
      }
    },
    {
      "description": "Read first time and referred to Committee on Natural Resources, Veteran and Military Affairs",
      "date": "2026-01-23T06:00:00+00:00",
      "organization_id": "~{\"classification\": \"upper\"}",
      "classification": [
        "reading-1",
        "referral-committee"
      ],
      "related_entities": [],
      "_processing": {
        "log_file_created": "2026-07-15T13:15:14Z"
      }
    },
    {
      "description": "Representative Anderson added as a cosponsor",
      "date": "2026-01-26T06:00:00+00:00",
      "organization_id": "~{\"classification\": \"upper\"}",
      "classification": [],
      "related_entities": [],
      "_processing": {
        "log_file_created": "2026-07-15T13:15:14Z"
      }
    },
    {
      "description": "Representative Clancy added as a cosponsor",
      "date": "2026-02-02T06:00:00+00:00",
      "organization_id": "~{\"classification\": \"upper\"}",
      "classification": [],
      "related_entities": [],
      "_processing": {
        "log_file_created": "2026-07-15T13:15:14Z"
      }
    },
    {
      "description": "Fiscal estimate received",
      "date": "2026-02-04T06:00:00+00:00",
      "organization_id": "~{\"classification\": \"upper\"}",
      "classification": [
        "receipt"
      ],
      "related_entities": [],
      "_processing": {
        "log_file_created": "2026-07-15T13:15:14Z"
      }
    },
    {
      "description": "Senator Habush Sinykin added as a coauthor",
      "date": "2026-03-19T05:00:00+00:00",
      "organization_id": "~{\"classification\": \"upper\"}",
      "classification": [],
      "related_entities": [],
      "_processing": {
        "log_file_created": "2026-07-15T13:15:14Z"
      }
    },
    {
      "description": "Representative Mayadev added as a cosponsor",
      "date": "2026-03-19T05:00:00+00:00",
      "organization_id": "~{\"classification\": \"upper\"}",
      "classification": [],
      "related_entities": [],
      "_processing": {
        "log_file_created": "2026-07-15T13:15:14Z"
      }
    },
    {
      "description": "Failed to pass pursuant to Senate Joint Resolution 1",
      "date": "2026-03-23T05:00:00+00:00",
      "organization_id": "~{\"classification\": \"upper\"}",
      "classification": [
        "failure"
      ],
      "related_entities": [],
      "_processing": {
        "log_file_created": "2026-07-15T13:15:14Z"
      }
    }
  ],
  "sponsorships": [
    {
      "name": "Drake",
      "classification": "primary",
      "entity_type": "person",
      "primary": true,
      "person_id": "~{\"chamber\": \"upper\", \"name\": \"Drake\"}",
      "organization_id": null
    },
    {
      "name": "Carpenter",
      "classification": "primary",
      "entity_type": "person",
      "primary": true,
      "person_id": "~{\"chamber\": \"upper\", \"name\": \"Carpenter\"}",
      "organization_id": null
    },
    {
      "name": "Hesselbein",
      "classification": "primary",
      "entity_type": "person",
      "primary": true,
      "person_id": "~{\"chamber\": \"upper\", \"name\": \"Hesselbein\"}",
      "organization_id": null
    },
    {
      "name": "L. Johnson",
      "classification": "primary",
      "entity_type": "person",
      "primary": true,
      "person_id": "~{\"chamber\": \"upper\", \"name\": \"L. Johnson\"}",
      "organization_id": null
    },
    {
      "name": "Larson",
      "classification": "primary",
      "entity_type": "person",
      "primary": true,
      "person_id": "~{\"chamber\": \"upper\", \"name\": \"Larson\"}",
      "organization_id": null
    },
    {
      "name": "Roys",
      "classification": "primary",
      "entity_type": "person",
      "primary": true,
      "person_id": "~{\"chamber\": \"upper\", \"name\": \"Roys\"}",
      "organization_id": null
    },
    {
      "name": "Smith",
      "classification": "primary",
      "entity_type": "person",
      "primary": true,
      "person_id": "~{\"chamber\": \"upper\", \"name\": \"Smith\"}",
      "organization_id": null
    },
    {
      "name": "Wall",
      "classification": "primary",
      "entity_type": "person",
      "primary": true,
      "person_id": "~{\"chamber\": \"upper\", \"name\": \"Wall\"}",
      "organization_id": null
    }
  ],
  "related_bills": [],
  "versions": [
    {
      "note": "Bill Text",
      "links": [
        {
          "url": "https://docs.legis.wisconsin.gov/document/proposaltext/2025/REG/SB867",
          "media_type": "text/html"
        },
        {
          "url": "https://docs.legis.wisconsin.gov/document/proposaltext/2025/REG/SB867.pdf",
          "media_type": "application/pdf"
        }
      ],
      "date": "",
      "classification": ""
    }
  ],
  "documents": [
    {
      "note": "SB867: Fiscal Estimate From DNR",
      "links": [
        {
          "url": "https://docs.legis.wisconsin.gov/2025/related/fe/sb867/sb867_dnr.pdf",
          "media_type": ""
        }
      ],
      "date": "",
      "classification": ""
    },
    {
      "note": "SB867 ROCP for Committee on Natural Resources, Veteran and Military Affairs",
      "links": [
        {
          "url": "https://docs.legis.wisconsin.gov/2025/related/records/senate/natural_resources_veteran_and_military_affairs/1985562",
          "media_type": "text/html"
        }
      ],
      "date": "",
      "classification": ""
    },
    {
      "note": "Wisconsin Ethics Commission information",
      "links": [
        {
          "url": "https://lobbying.wi.gov/What/BillInformation/2025REG/BillKey/REGSB867",
          "media_type": "text/html"
        }
      ],
      "date": "",
      "classification": ""
    },
    {
      "note": "2025 Assembly Bill 879",
      "links": [
        {
          "url": "https://docs.legis.wisconsin.gov/2025/proposals/ab879",
          "media_type": "text/html"
        }
      ],
      "date": "",
      "classification": ""
    }
  ],
  "citations": [],
  "sources": [
    {
      "url": "https://docs.legis.wisconsin.gov/2025/proposals/reg/sen/bill/sb867",
      "note": ""
    }
  ],
  "extras": {
    "status": "Status: S - Natural Resources, Veteran and Military Affairs"
  },
  "jurisdiction": {
    "id": "ocd-jurisdiction/country:us/state:wi/government",
    "name": "Wisconsin",
    "classification": "state",
    "division_id": "ocd-division/country:us/state:wi"
  },
  "_processing": {
    "logs_latest_update": "2026-07-15T13:15:14Z"
  }
}